spyder_watchlist/__init__.py
spyder_watchlist/plugin.py
spyder_watchlist/locale/spyder_watchlist.pot
spyder_watchlist/locale/de/LC_MESSAGES/spyder_watchlist.mo
spyder_watchlist/locale/de/LC_MESSAGES/spyder_watchlist.po
spyder_watchlist/widgets/__init__.py
spyder_watchlist/widgets/kernel_backend.py
spyder_watchlist/widgets/main_widget.py
spyder_watchlist/widgets/watchlist.py
spyder_watchlist-1.1.1.dist-info/entry_points.txt
spyder_watchlist-1.1.1.dist-info/LICENSE
spyder_watchlist-1.1.1.dist-info/WHEEL
spyder_watchlist-1.1.1.dist-info/METADATA
spyder_watchlist-1.1.1.dist-info/RECORD
