Metadata-Version: 2.3
Name: spyder-watchlist
Version: 1.1.1
Summary: Watchlist plugin for the debugger in the Spyder IDE
Keywords: Spyder,watchlist,debugger
Maintainer-email: "A. Reit" <a.reit@procitec.de>
Requires-Python: >=3.7
Classifier: License :: OSI Approved :: MIT License
Classifier: Development Status :: 5 - Production/Stable
Classifier: Programming Language :: Python :: 3 :: Only
Classifier: Operating System :: OS Independent
Classifier: Topic :: Text Editors :: Integrated Development Environments (IDE)
Classifier: Topic :: Software Development :: Debuggers
Requires-Dist: spyder>=5.3,<6
Requires-Dist: spyder-kernels>=2.3,<3
Project-URL: Changelog, https://github.com/procitec/spyder-watchlist/blob/main/CHANGELOG.md
Project-URL: Source, https://github.com/procitec/spyder-watchlist
